{
  "name": "Bullitt",
  "Rating:": "PG",
  "Genre:": "Drama, \n                        \n                        Crime",
  "Original Language:": "English",
  "Director:": "Peter Yates",
  "Producer:": "Philip D'Antoni",
  "Writer:": "Robert L. Pike, \n                            \n                        \n                            \n                                Alan R. Trustman, \n                            \n                        \n                            \n                                Harry Kleiner",
  "Release Date (Theaters):": "Oct 17, 1968\n\u00a0wide",
  "Release Date (Streaming):": "Sep 15, 1998",
  "Runtime:": "1h 53m",
  "Distributor:": "Warner Bros. Pictures",
  "Sound Mix:": "Stereo",
  "Aspect Ratio:": "Flat (1.85:1)"
}